ktdk/__init__.py
ktdk/config.py
ktdk/log_config.py
ktdk/version.py
ktdk/asserts/__init__.py
ktdk/asserts/utils.py
ktdk/asserts/checks/__init__.py
ktdk/asserts/checks/executable.py
ktdk/asserts/checks/general.py
ktdk/asserts/checks/junit.py
ktdk/asserts/checks/style.py
ktdk/asserts/matchers/__init__.py
ktdk/asserts/matchers/basic.py
ktdk/asserts/matchers/files.py
ktdk/asserts/matchers/general.py
ktdk/asserts/matchers/suite.py
ktdk/cli/__init__.py
ktdk/cli/__main__.py
ktdk/cli/manager.py
ktdk/cli/printer.py
ktdk/core/__init__.py
ktdk/core/abstract.py
ktdk/core/errors.py
ktdk/core/mixins.py
ktdk/core/reporters.py
ktdk/core/results.py
ktdk/core/tasks.py
ktdk/core/tests.py
ktdk/declarative/__init__.py
ktdk/declarative/base.py
ktdk/declarative/registry.py
ktdk/declarative/resolvers.py
ktdk/declarative/yaml_extend.py
ktdk/resources/config/defaults.yml
ktdk/runtime/__init__.py
ktdk/runtime/context.py
ktdk/runtime/runners.py
ktdk/runtime/stat.py
ktdk/runtime/tags.py
ktdk/scenarios/__init__.py
ktdk/scenarios/scenario.py
ktdk/scenarios/simple.py
ktdk/scenarios/c/__init__.py
ktdk/scenarios/c/mini.py
ktdk/scenarios/cpp/__init__.py
ktdk/scenarios/cpp/mini.py
ktdk/scenarios/cpp/stylecheck.py
ktdk/tasks/__init__.py
ktdk/tasks/build_task.py
ktdk/tasks/command.py
ktdk/tasks/command_task.py
ktdk/tasks/cpp/__init__.py
ktdk/tasks/cpp/catch.py
ktdk/tasks/cpp/checkstyle.py
ktdk/tasks/cpp/cmake.py
ktdk/tasks/cpp/compiler.py
ktdk/tasks/cpp/valgrind.py
ktdk/tasks/fs/__init__.py
ktdk/tasks/fs/tasks.py
ktdk/tasks/fs/tools.py
ktdk/tasks/java/__init__.py
ktdk/tasks/java/maven.py
ktdk/tasks/python/__init__.py
ktdk/tasks/python/pytest.py
ktdk/tasks/raw/__init__.py
ktdk/tasks/raw/executable.py
ktdk/tasks/ruby/__init__.py
ktdk/tasks/ruby/rake.py
ktdk/tasks/xunit/__init__.py
ktdk/tasks/xunit/junit.py
ktdk/utils/__init__.py
ktdk/utils/basic.py
ktdk/utils/file_utils.py
ktdk/utils/flatters.py
ktdk/utils/meta_utils.py
ktdk/utils/naming.py
ktdk/utils/serialization.py
tests/assertions/__init__.py
ktdk-0.4.2.dist-info/AUTHORS
ktdk-0.4.2.dist-info/LICENSE
ktdk-0.4.2.dist-info/METADATA
ktdk-0.4.2.dist-info/WHEEL
ktdk-0.4.2.dist-info/entry_points.txt
ktdk-0.4.2.dist-info/top_level.txt
ktdk-0.4.2.dist-info/RECORD
