Metadata-Version: 2.1
Name: ktdk
Version: 0.4.2
Summary: Kontr tests development kit
Home-page: https://gitlab.fi.muni.cz/grp-kontr2/ktdk
Author: Peter Stanko
Author-email: stanko@mail.muni.cz
License: UNKNOWN
Platform: UNKNOWN
Classifier: Programming Language :: Python :: 3
Classifier: Programming Language :: Python :: 3.6
Classifier: Programming Language :: Python :: 3.7
Classifier: Operating System :: OS Independent
Classifier: License :: OSI Approved :: Apache Software License
Classifier: Intended Audience :: Developers
Classifier: Topic :: Utilities
Requires-Dist: unidecode
Requires-Dist: junitparser
Requires-Dist: pyyaml
Requires-Dist: IntelHex
Requires-Dist: click
Requires-Dist: requests
Requires-Dist: coloredlogs
Provides-Extra: dev
Requires-Dist: pytest (>=3) ; extra == 'dev'
Requires-Dist: coverage ; extra == 'dev'
Requires-Dist: pytest-cov ; extra == 'dev'
Requires-Dist: pytest-mock ; extra == 'dev'
Provides-Extra: docs
Requires-Dist: sphinx ; extra == 'docs'
